{"cameraMode":{"drawMode":0,"name":"Shaded","section":"Shading Mode"},"sceneLighting":false,"audioPlay":false,"sceneViewState":{"m_AlwaysRefresh":false,"showFog":true,"showSkybox":false,"showFlares":true,"showImageEffects":true,"showParticleSystems":true,"showVisualEffectGraphs":true,"m_FxEnabled":true},"in2DMode":false,"pivot":{"x":-2.002600908279419,"y":8.444608688354493,"z":50.20250701904297},"rotation":{"x":0.0011359610361978412,"y":0.9389187693595886,"z":-0.3441263735294342,"w":0.00309946876950562},"size":16.187023162841798,"orthographic":false}